[
  {
    "_id": "5f7adbcf93731f3085b79055",
    "name": "NodeJS",
    "__v": 0
  },
  {
    "_id": "5f7adbd793731f3085b79056",
    "name": "ReactJS",
    "__v": 0
  },
  {
    "_id": "5f7adbe093731f3085b79057",
    "name": "MongoDB",
    "__v": 0
  },
  {
    "_id": "5f7adbe693731f3085b79058",
    "name": "MySQL",
    "__v": 0
  },
  {
    "_id": "5f7adbeb93731f3085b79059",
    "name": "SEO",
    "__v": 0
  },
  {
    "_id": "5f7adbf593731f3085b7905a",
    "name": "HTML",
    "__v": 0
  },
  {
    "_id": "5f7adbf993731f3085b7905b",
    "name": "CSS",
    "__v": 0
  },
  {
    "_id": "5f7adc0193731f3085b7905c",
    "name": "JavaScript",
    "__v": 0
  },
  {
    "_id": "5f7adc0993731f3085b7905d",
    "name": "C",
    "__v": 0
  },
  {
    "_id": "5f7adc0d93731f3085b7905e",
    "name": "C++",
    "__v": 0
  },
  {
    "_id": "5f7adc1493731f3085b7905f",
    "name": "Java",
    "__v": 0
  },
  {
    "_id": "5f7adc1b93731f3085b79060",
    "name": "Python",
    "__v": 0
  },
  {
    "_id": "5f7adc2593731f3085b79061",
    "name": "Ruby",
    "__v": 0
  },
  {
    "_id": "5f7adc2c93731f3085b79062",
    "name": "Swift",
    "__v": 0
  },
  {
    "_id": "5f7adc4b93731f3085b79063",
    "name": "Django",
    "__v": 0
  },
  {
    "_id": "5f7adc5293731f3085b79064",
    "name": "PHP",
    "__v": 0
  },
  {
    "_id": "5f7adc6793731f3085b79065",
    "name": "React Native",
    "__v": 0
  },
  {
    "_id": "5f7adc6c93731f3085b79066",
    "name": "Flutter",
    "__v": 0
  },
  {
    "_id": "5f7adc7293731f3085b79067",
    "name": "Go",
    "__v": 0
  },
  {
    "_id": "5f7adc7a93731f3085b79068",
    "name": "ElectronJS",
    "__v": 0
  },
  {
    "_id": "5f7af086622b203cf508309c",
    "name": "Adaptability",
    "__v": 0
  },
  {
    "_id": "5f7af090622b203cf508309d",
    "name": "Blockchain",
    "__v": 0
  },
  {
    "_id": "5f7af099622b203cf508309e",
    "name": "Cloud Computing",
    "__v": 0
  },
  {
    "_id": "5f7af0ae622b203cf508309f",
    "name": "Machine Learning",
    "__v": 0
  },
  {
    "_id": "5f7af0bd622b203cf50830a0",
    "name": "Artificial Intelligence",
    "__v": 0
  },
  {
    "_id": "5f7af102622b203cf50830a1",
    "name": "Video Editing",
    "__v": 0
  },
  {
    "_id": "5f7af113622b203cf50830a2",
    "name": "Web Development",
    "__v": 0
  },
  {
    "_id": "5f7af124622b203cf50830a3",
    "name": "iOs Development",
    "__v": 0
  },
  {
    "_id": "5f7af12d622b203cf50830a4",
    "name": "Pentesting",
    "__v": 0
  },
  {
    "_id": "5f7af133622b203cf50830a5",
    "name": "Debugging",
    "__v": 0
  },
  {
    "_id": "5f7af1b2622b203cf50830a6",
    "name": "Data Analysis",
    "__v": 0
  },
  {
    "_id": "5f7af1be622b203cf50830a7",
    "name": "Analytical Skills",
    "__v": 0
  },
  {
    "_id": "5f7af1dc622b203cf50830a8",
    "name": "C#",
    "__v": 0
  },
  {
    "_id": "5f7af1fa622b203cf50830a9",
    "name": "Software Development",
    "__v": 0
  },
  {
    "_id": "5f7af204622b203cf50830aa",
    "name": "Android Development",
    "__v": 0
  },
  {
    "_id": "5f7af241622b203cf50830ab",
    "name": "Graphics",
    "__v": 0
  },
  {
    "_id": "5f7af28c622b203cf50830ac",
    "name": "jQuery",
    "__v": 0
  },
  {
    "_id": "5f7af291622b203cf50830ad",
    "name": "sass",
    "__v": 0
  },
  {
    "_id": "5f7af29a622b203cf50830ae",
    "name": "Bootstrap",
    "__v": 0
  },
  {
    "_id": "5f7af2b4622b203cf50830af",
    "name": "Kubernetes",
    "__v": 0
  },
  {
    "_id": "5f7af2bb622b203cf50830b0",
    "name": "Docker",
    "__v": 0
  },
  {
    "_id": "5f7af2e2622b203cf50830b1",
    "name": "Networking",
    "__v": 0
  },
  {
    "_id": "5f7af2e9622b203cf50830b2",
    "name": "Security",
    "__v": 0
  },
  {
    "_id": "5f7af308622b203cf50830b3",
    "name": "R",
    "__v": 0
  },
  {
    "_id": "5f7af347622b203cf50830b4",
    "name": "Web Services",
    "__v": 0
  },
  {
    "_id": "5f7af5bb8d065e402cbe808f",
    "name": "IOT",
    "__v": 0
  },
  {
    "_id": "5f7af5c98d065e402cbe8090",
    "name": "Robotics",
    "__v": 0
  },
  {
    "_id": "5f7af5d38d065e402cbe8091",
    "name": "Data Structures",
    "__v": 0
  },
  {
    "_id": "5f7af5db8d065e402cbe8092",
    "name": "Algorithms",
    "__v": 0
  },
  {
    "_id": "5f7af60b8d065e402cbe8093",
    "name": "Problem Solving",
    "__v": 0
  },
  {
    "_id": "5f7af6208d065e402cbe8094",
    "name": "Git",
    "__v": 0
  },
  {
    "_id": "5f7af6348d065e402cbe8095",
    "name": "Amazon Web Services",
    "__v": 0
  },
  {
    "_id": "5f7af65c8d065e402cbe8096",
    "name": "AngularJS",
    "__v": 0
  },
  {
    "_id": "5f7af6898d065e402cbe8097",
    "name": "Perl",
    "__v": 0
  },
  {
    "_id": "5f7af6918d065e402cbe8098",
    "name": "SQL",
    "__v": 0
  },
  {
    "_id": "5f7af6a28d065e402cbe8099",
    "name": "PostgreSQL",
    "__v": 0
  },
  {
    "_id": "5f7af6fa8d065e402cbe809a",
    "name": "Bash",
    "__v": 0
  },
  {
    "_id": "5f7af7218d065e402cbe809b",
    "name": "Dart",
    "__v": 0
  },
  {
    "_id": "5f7af7358d065e402cbe809c",
    "name": "Game Development",
    "__v": 0
  },
  {
    "_id": "5f7af7528d065e402cbe809d",
    "name": "Operating System",
    "__v": 0
  },
  {
    "_id": "5f7af77c8d065e402cbe809e",
    "name": "Quantum Computation",
    "__v": 0
  },
  {
    "_id": "5f7af7838d065e402cbe809f",
    "name": "Big Data",
    "__v": 0
  },
  {
    "_id": "5f7af7948d065e402cbe80a0",
    "name": "Rust",
    "__v": 0
  },
  {
    "_id": "5f7af7ab8d065e402cbe80a1",
    "name": "XML",
    "__v": 0
  },
  {
    "_id": "5f7af7cf8d065e402cbe80a2",
    "name": "Assembly",
    "__v": 0
  },
  {
    "_id": "5f7af7f08d065e402cbe80a3",
    "name": "Haskell",
    "__v": 0
  },
  {
    "_id": "5f7af7f58d065e402cbe80a4",
    "name": "Kotlin",
    "__v": 0
  }
]